{
  "$schema": "https://raw.githubusercontent.com/grafana/grafana/main/docs/sources/developers/plugins/plugin.schema.json",
  "type": "datasource",
  "name": "Ingero",
  "id": "ingero-gpu-datasource",
  "metrics": true,
  "backend": true,
  "executable": "gpx_ingero_gpu",
  "info": {
    "description": "Native datasource for Ingero Echo. Query the Echo DuckDB store via SQL, invoke MCP tools as panel data, and surface the anomaly stream with structured rows.",
    "keywords": ["nvidia", "gpu", "cuda", "nccl", "ebpf", "ingero", "echo", "mcp"],
    "author": {
      "name": "Ingero",
      "url": "https://github.com/ingero-io"
    },
    "logos": {
      "small": "img/logo.svg",
      "large": "img/logo.svg"
    },
    "links": [
      {
        "name": "GitHub",
        "url": "https://github.com/ingero-io/ingero-grafana-app"
      }
    ],
    "screenshots": [],
    "version": "%VERSION%",
    "updated": "%TODAY%"
  },
  "dependencies": {
    "grafanaDependency": ">=12.3.0",
    "plugins": []
  }
}
